[
  {
    "id": 1,
    "title": "心衰患者联合用药致高钾血症",
    "description": "患者，男，68岁，诊断为慢性心力衰竭伴高血压。长期服用卡托普利(ACE抑制药)控制血压和心衰。因踝部水肿加用螺内酯利尿。用药1周后出现乏力、心悸、四肢麻木，ECG示T波高尖，血钾6.8mmol/L。",
    "drugs": [
      "卡托普利",
      "螺内酯"
    ]
  },
  {
    "id": 2,
    "title": "感染患者饮酒致双硫仑样反应",
    "description": "患者，女，35岁，因上呼吸道感染口服头孢呋辛治疗。用药期间参加聚会饮用红酒约100ml。15分钟后出现面部潮红、剧烈头痛、恶心呕吐、胸闷气短、心率加快(120次/分)，血压下降至85/50mmHg。",
    "drugs": [
      "头孢呋辛"
    ]
  },
  {
    "id": 3,
    "title": "房颤患者联合抗凝致消化道出血",
    "description": "患者，女，72岁，因房颤长期口服华法林抗凝。近期关节痛自行加用阿司匹林肠溶片。3天后出现黑色柏油样便，伴头晕、乏力。查INR 4.5，Hb 85g/L，粪便OB(+++)。",
    "drugs": [
      "华法林",
      "阿司匹林"
    ]
  },
  {
    "id": 4,
    "title": "老年房颤患者NSAID致消化道出血",
    "description": "患者，女，78岁，心房颤动长期口服华法林抗凝。因膝关节疼痛自行加用布洛芬缓释胶囊。1周后出现黑便、头晕、乏力。查体：面色苍白，BP 90/60mmHg，Hb 75g/L，INR 3.8，粪便隐血(+++)。",
    "drugs": [
      "华法林",
      "布洛芬"
    ]
  },
  {
    "id": 5,
    "title": "心衰患者ACEI联合螺内酯致高钾血症",
    "description": "患者，男，65岁，慢性心力衰竭（NYHA III级）长期口服卡托普利和螺内酯。近1周出现乏力、四肢麻木、心悸。查体：心率55次/分，ECG示T波高尖、QRS增宽。血钾6.9mmol/L。",
    "drugs": [
      "卡托普利",
      "螺内酯"
    ]
  },
  {
    "id": 6,
    "title": "术后患者阿片类联用苯二氮䓬类致呼吸抑制",
    "description": "患者，男，45岁，腰椎术后使用吗啡镇痛，因焦虑加用地西泮。用药后出现嗜睡、呼吸浅慢。查体：R 8次/分，SpO₂ 85%，双侧瞳孔针尖样缩小。",
    "drugs": [
      "吗啡",
      "地西泮"
    ]
  },
  {
    "id": 7,
    "title": "消化科患者多潘立酮联用抗真菌药致QT延长",
    "description": "患者，女，52岁，因胃食管反流病口服多潘立酮。因念珠菌性阴道炎加用酮康唑。用药3天后出现心悸、头晕。ECG示QTc 510ms，频发室性早搏。",
    "drugs": [
      "多潘立酮",
      "酮康唑"
    ]
  },
  {
    "id": 8,
    "title": "心衰患者地高辛联用利尿剂致洋地黄中毒",
    "description": "患者，男，72岁，慢性心衰长期服用地高辛，因下肢水肿加用呋塞米。1周后出现恶心呕吐、黄视、频发室早二联律。血地高辛浓度3.2ng/ml(正常0.8-2.0)，血钾3.1mmol/L。",
    "drugs": [
      "地高辛",
      "呋塞米"
    ]
  },
  {
    "id": 9,
    "title": "感染患者使用头孢菌素后饮酒致双硫仑样反应",
    "description": "患者，男，38岁，因社区获得性肺炎静脉输注头孢曲松。治疗后第2天参加宴会饮酒约150ml，15分钟后突发面部潮红、胸闷气短、剧烈头痛、恶心呕吐。BP 85/50mmHg，HR 125次/分。",
    "drugs": [
      "头孢曲松"
    ]
  },
  {
    "id": 10,
    "title": "结核患者INH联合利福平致药物性肝损害",
    "description": "患者，男，33岁，新诊断肺结核，采用异烟肼+利福平+吡嗪酰胺+乙胺丁醇方案。治疗3周后出现乏力、食欲减退、尿黄。ALT 385U/L，AST 420U/L，TBil 68μmol/L。",
    "drugs": [
      "异烟肼",
      "利福平"
    ]
  },
  {
    "id": 11,
    "title": "感染患者氨基糖苷类联用袢利尿剂致肾损害",
    "description": "患者，女，60岁，胆道感染使用庆大霉素，因水肿联合呋塞米。治疗5天后尿量减少至400ml/日，血肌酐由82μmol/L升至356μmol/L，伴耳鸣。",
    "drugs": [
      "庆大霉素",
      "呋塞米"
    ]
  },
  {
    "id": 12,
    "title": "心肌梗死患者PPI联用氯吡格雷降低疗效",
    "description": "患者，男，58岁，急性ST段抬高型心梗行PCI术后，双抗(阿司匹林+氯吡格雷)治疗，因胃部不适加用奥美拉唑。随访发现血小板抑制率仅28%(目标>50%)。",
    "drugs": [
      "氯吡格雷",
      "奥美拉唑"
    ]
  },
  {
    "id": 13,
    "title": "糖尿病患者饮酒后致严重低血糖",
    "description": "患者，男，50岁，2型糖尿病口服格列本脲控制血糖。参加聚会喝白酒约100ml，2小时后出现大汗淋漓、心悸、手抖、意识模糊。指尖血糖1.8mmol/L。",
    "drugs": [
      "格列本脲"
    ]
  },
  {
    "id": 14,
    "title": "糖尿病患者β受体阻断药掩盖低血糖症状",
    "description": "患者，女，55岁，2型糖尿病使用胰岛素控制血糖，合并冠心病口服普萘洛尔。某次发生低血糖(血糖2.5mmol/L)但无心悸、手抖等早期症状，仅表现为嗜睡，被家属及时发现。",
    "drugs": [
      "普萘洛尔",
      "胰岛素"
    ]
  },
  {
    "id": 15,
    "title": "止吐药联用抗精神病药致严重锥体外系反应",
    "description": "患者，女，28岁，因偏头痛呕吐肌注甲氧氯普胺，因精神分裂症长期口服氯丙嗪。用药后出现颈部歪斜、双眼上翻、牙关紧闭及肢体僵硬。",
    "drugs": [
      "甲氧氯普胺",
      "氯丙嗪"
    ]
  }
]